jupyter_cpu_alive/__init__.py
jupyter_cpu_alive-0.1.6.data/data/etc/jupyter/jupyter_server_config.d/jupyter_cpu_alive.json
jupyter_cpu_alive-0.1.6.dist-info/METADATA
jupyter_cpu_alive-0.1.6.dist-info/WHEEL
jupyter_cpu_alive-0.1.6.dist-info/licenses/LICENSE
jupyter_cpu_alive-0.1.6.dist-info/RECORD
