Metadata-Version: 2.4
Name: jupyter_cpu_alive
Version: 0.1.6
Summary: A Jupyter Server extension that accesses and modifies the settings dictionary.
Project-URL: homepage, https://example.com/jupyter_cpu_alive
Project-URL: source, https://github.com/yourusername/jupyter_cpu_alive
Project-URL: tracker, https://github.com/yourusername/jupyter_cpu_alive/issues
Author-email: Your Name <your.email@example.com>
License: MIT
License-File: LICENSE
Requires-Dist: jupyter-server>=2.0
